boxb/__init__.py
lagh-1.0.0.dist-info/METADATA
lagh-1.0.0.dist-info/RECORD
lagh-1.0.0.dist-info/WHEEL
lagh-1.0.0.dist-info/top_level.txt
